libsoc_zero/GPIO.py
libsoc_zero/SPI.py
libsoc_zero/__init__.py
libsoc_zero-0.0.3.dist-info/DESCRIPTION.rst
libsoc_zero-0.0.3.dist-info/METADATA
libsoc_zero-0.0.3.dist-info/RECORD
libsoc_zero-0.0.3.dist-info/WHEEL
libsoc_zero-0.0.3.dist-info/metadata.json
libsoc_zero-0.0.3.dist-info/top_level.txt
