Metadata-Version: 2.0
Name: libsoc-zero
Version: 0.0.3
Summary: For using GPIO on 96boards
Home-page: https://github.com/DBOpenSource/linker_starter_kit
Author: Barry Byford
Author-email: barry_byford@yahoo.co.uk
License: BSD
Keywords: GPIO 96boards development
Platform: UNKNOWN
Classifier: Development Status :: 3 - Alpha
Classifier: Intended Audience :: Developers
Classifier: Intended Audience :: Education
Classifier: Topic :: System :: Hardware
Classifier: Topic :: Software Development :: Embedded Systems
Classifier: Topic :: Home Automation
Classifier: Topic :: Education
Classifier: License :: OSI Approved :: BSD License
Classifier: Programming Language :: Python :: 2.7
Classifier: Programming Language :: Python :: 3
